[
	{"user":"janine","pword":"n4621"},
	{"user":"jennielyn","pword":"1f738"},
	{"user":"Rhea","pword":"z3278"},
	{"user":"Maviross","pword":"352j8"},
	{"user":"samantha","pword":"246q0"},
	{"user":"steph","pword":"189n4"},
	{"user":"charina","pword":"1p307"},
	{"user":"myra","pword":"3031s"},
	{"user":"kevin","pword":"b0043"},
	{"user":"isai.pay","pword":"0v564"},
	{"user":"felix","pword":"t0273"},
	{"user":"jeffry.pay","pword":"1z448"},
	{"user":"Hery","pword":"5s188"},
	{"user":"jecky","pword":"r6729"},
	{"user":"chardih.cs","pword":"r5109"},
	{"user":"lius","pword":"x0664"},
	{"user":"vera.cs","pword":"4k309"},
	{"user":"shendy","pword":"4i887"},
	{"user":"hendry","pword":"67a15"},
	{"user":"yohana","pword":"78o12"},
	{"user":"julieth","pword":"w3uho"}
]